sqlwriter/__init__.py
sqlwriter/utils.py
sqlwriter/writers.py
sqlwriter-1.0.1.dist-info/DESCRIPTION.rst
sqlwriter-1.0.1.dist-info/METADATA
sqlwriter-1.0.1.dist-info/RECORD
sqlwriter-1.0.1.dist-info/WHEEL
sqlwriter-1.0.1.dist-info/metadata.json
sqlwriter-1.0.1.dist-info/top_level.txt
