Metadata-Version: 2.0
Name: sqlwriter
Version: 1.0.1
Summary: Writes pandas DataFrame to several flavors of sql database
Home-page: UNKNOWN
Author: Sebastian Estenssoro
Author-email: seb.estenssoro@gmail.com
License: MIT
Platform: UNKNOWN
Classifier: License :: OSI Approved :: MIT License
Classifier: Programming Language :: Python :: 2.7
